anonipy/__init__.py
anonipy/constants.py
anonipy/definitions.py
anonipy/anonymize/__init__.py
anonipy/anonymize/helpers.py
anonipy/anonymize/pipeline.py
anonipy/anonymize/extractors/__init__.py
anonipy/anonymize/extractors/interface.py
anonipy/anonymize/extractors/multi_extractor.py
anonipy/anonymize/extractors/ner_extractor.py
anonipy/anonymize/extractors/pattern_extractor.py
anonipy/anonymize/generators/__init__.py
anonipy/anonymize/generators/date_generator.py
anonipy/anonymize/generators/interface.py
anonipy/anonymize/generators/llm_label_generator.py
anonipy/anonymize/generators/mask_label_generator.py
anonipy/anonymize/generators/number_generator.py
anonipy/anonymize/strategies/__init__.py
anonipy/anonymize/strategies/interface.py
anonipy/anonymize/strategies/masking.py
anonipy/anonymize/strategies/pseudonymization.py
anonipy/anonymize/strategies/redaction.py
anonipy/utils/__init__.py
anonipy/utils/colors.py
anonipy/utils/datetime_format.py
anonipy/utils/file_system.py
anonipy/utils/language_detector.py
anonipy/utils/package.py
anonipy/utils/regex.py
anonipy-0.6.0.dist-info/licenses/LICENSE
anonipy-0.6.0.dist-info/METADATA
anonipy-0.6.0.dist-info/WHEEL
anonipy-0.6.0.dist-info/top_level.txt
anonipy-0.6.0.dist-info/RECORD
