Metadata-Version: 2.4
Name: anonipy
Version: 0.6.0
Summary: The data anonymization package
Author: Erik Novak, Nina Kokalj
Maintainer: Erik Novak
License: BSD 2-Clause License
Project-URL: Source, https://github.com/eriknovak/anonipy
Project-URL: Docs, https://eriknovak.github.io/anonipy
Keywords: python,machine learning,natural language processing,anonymization
Classifier: Intended Audience :: Developers
Classifier: Intended Audience :: Science/Research
Classifier: Programming Language :: Python :: 3.10
Classifier: Programming Language :: Python :: 3.11
Classifier: Programming Language :: Python :: 3.12
Classifier: Programming Language :: Python :: 3.13
Classifier: License :: OSI Approved :: BSD License
Classifier: Operating System :: OS Independent
Classifier: Topic :: Scientific/Engineering :: Artificial Intelligence
Classifier: Topic :: Text Processing :: Linguistic
Requires-Python: >=3.10
License-File: LICENSE
Requires-Dist: spacy>=3.8.8
Requires-Dist: gliner>=0.2.22
Requires-Dist: gliner-spacy>=0.0.11
Requires-Dist: transformers==4.45.2
Requires-Dist: sentencepiece>=0.2.1
Requires-Dist: accelerate>=0.26.0
Requires-Dist: lingua-language-detector>=2.1.1
Requires-Dist: python-dateutil>=2.9.0
Requires-Dist: babel>=2.13.0
Requires-Dist: dateparser>=1.2.2
Requires-Dist: pypdf>=4.2.0
Requires-Dist: python-docx>=1.1.2
Requires-Dist: tqdm==4.67.1
Provides-Extra: dev
Requires-Dist: black; extra == "dev"
Requires-Dist: flake8; extra == "dev"
Requires-Dist: python-githooks; extra == "dev"
Requires-Dist: mkdocs-material; extra == "dev"
Requires-Dist: mkdocstrings[python]; extra == "dev"
Requires-Dist: mkdocs-git-revision-date-localized-plugin; extra == "dev"
Requires-Dist: mkdocs-minify-plugin; extra == "dev"
Provides-Extra: test
Requires-Dist: pytest; extra == "test"
Requires-Dist: pytest-cov; extra == "test"
Provides-Extra: quant
Requires-Dist: bitsandbytes; extra == "quant"
Provides-Extra: all
Requires-Dist: anonipy[dev,quant,test]; extra == "all"
Dynamic: license-file
